gmail_mcp_server/__init__.py
gmail_mcp_server/__main__.py
gmail_mcp_server/oauth.py
gmail_mcp_server/server.py
gmail_mcp_server/models/__init__.py
gmail_mcp_server/models/email_models.py
gmail_mcp_server/services/__init__.py
gmail_mcp_server/services/gmail_client.py
gmail_mcp_server/tools/__init__.py
gmail_mcp_server/tools/email_tools.py
gmail_mcp_server/utils/__init__.py
gmail_mcp_server/utils/config.py
gmail_mcp_server_ansh-1.0.5.dist-info/licenses/LICENSE
gmail_mcp_server_ansh-1.0.5.dist-info/METADATA
gmail_mcp_server_ansh-1.0.5.dist-info/WHEEL
gmail_mcp_server_ansh-1.0.5.dist-info/entry_points.txt
gmail_mcp_server_ansh-1.0.5.dist-info/top_level.txt
gmail_mcp_server_ansh-1.0.5.dist-info/RECORD
