Metadata-Version: 2.4
Name: gmail-mcp-server-ansh
Version: 1.0.5
Summary: A Model Context Protocol (MCP) server for Gmail integration.
Author: Gmail MCP Server Team
License: MIT License
Project-URL: Homepage, https://github.com/Ansh-Wappnet/gmail_mcp_server
Requires-Python: >=3.10
License-File: LICENSE
Requires-Dist: openai
Requires-Dist: fastapi
Requires-Dist: fastmcp
Requires-Dist: uvicorn
Requires-Dist: google-api-python-client
Requires-Dist: google-auth
Requires-Dist: google-auth-oauthlib
Requires-Dist: google-auth-httplib2
Requires-Dist: sse-starlette
Requires-Dist: groq
Requires-Dist: pydantic-settings
Dynamic: license-file
